Metadata-Version: 2.1
Name: ESGmetric-from-PDF
Version: 0.1
Summary: Extracting ESG metrics from a PDF
Home-page: UNKNOWN
Author: Sophia Moreton
License: UNKNOWN
Platform: UNKNOWN
